csv_adapter/__init__.py
csv_adapter/csv_parser.py
csv_adapter/csv_writer.py
csv_adapter/setup.py
csv_adapter/util.py
datamodel/__init__.py
datamodel/datamodel.py
datamodel/setup.py
datamodel/util.py
jarvis/__init__.py
jarvis/command_parser.py
jarvis/jarvis.py
jarvis/util.py
jarvis/diagram/__init__.py
jarvis/diagram/diagram_generator.py
jarvis/diagram/diagram_generator_chain.py
jarvis/diagram/diagram_generator_fana.py
jarvis/diagram/diagram_generator_farch.py
jarvis/diagram/util.py
jarvis/handler/__init__.py
jarvis/handler/handler_list.py
jarvis/handler/handler_question.py
jarvis/orchestrator/__init__.py
jarvis/orchestrator/orchestrator_dictionary.py
jarvis/orchestrator/orchestrator_functional.py
jarvis/orchestrator/orchestrator_object.py
jarvis/orchestrator/orchestrator_object_inheritance.py
jarvis/orchestrator/orchestrator_shared.py
jarvis/orchestrator/orchestrator_viewpoint.py
jarvis/orchestrator/orchestrator_viewpoint_attribute.py
jarvis/orchestrator/orchestrator_viewpoint_inheritance.py
jarvis/orchestrator/orchestrator_viewpoint_requirement.py
jarvis/orchestrator/orchestrator_viewpoint_type.py
jarvis/query/__init__.py
jarvis/query/query_inheritance.py
jarvis/query/query_object.py
jarvis/query/question_answer.py
jarvis/simulation/__init__.py
jarvis/simulation/simulation_generator.py
open_modelica_adapter/__init__.py
open_modelica_adapter/open_modelica_adapter.py
open_modelica_adapter/open_modelica_connector.py
open_modelica_adapter/util.py
plantuml_adapter/__init__.py
plantuml_adapter/plantuml_adapter.py
plantuml_adapter/plantuml_connector.py
plantuml_adapter/setup.py
plantuml_adapter/util.py
tools/__init__.py
tools/config.py
tools/console.py
tools/logger.py
tools/magic_tools.py
tools/util.py
xml_adapter/__init__.py
xml_adapter/setup.py
xml_adapter/util.py
xml_adapter/xml_parser.py
xml_adapter/xml_writer.py
jarvis4se-1.4.1.dist-info/LICENSE
jarvis4se-1.4.1.dist-info/METADATA
jarvis4se-1.4.1.dist-info/WHEEL
jarvis4se-1.4.1.dist-info/top_level.txt
jarvis4se-1.4.1.dist-info/RECORD
