Metadata-Version: 2.1
Name: jarvis4se
Version: 1.4.1
Summary: Jarvis 4 Systems Engineers
Home-page: https://github.com/rcasteran/jarvis4se
Author: Regis CASTERAN
Author-email: casteranregis@gmail.com
License: MIT
Project-URL: Bug Tracker, https://github.com/rcasteran/jarvis4se/issues
Project-URL: Gitbook, https://regis-casteran.gitbook.io/jarvis4se/
Classifier: License :: OSI Approved :: MIT License
Classifier: Operating System :: OS Independent
Classifier: Topic :: Scientific/Engineering :: Visualization
Classifier: Topic :: Software Development :: Libraries :: Python Modules
Classifier: Programming Language :: Python :: 3.8
Requires-Python: >=3.8
License-File: LICENSE
Requires-Dist: ipython>=7.27.0
Requires-Dist: lxml>=4.6.3
Requires-Dist: notebook>=6.4.3
Requires-Dist: plantuml>=0.3.0
Requires-Dist: pandas>=1.4.1
Requires-Dist: requests>=2.31.0
Requires-Dist: nltk>=3.9
